MANIFEST.in
README.md
setup.cfg
setup.py
mordecai/__init__.py
mordecai/geocode.py
mordecai/geoparse.py
mordecai/utilities.py
mordecai.egg-info/PKG-INFO
mordecai.egg-info/SOURCES.txt
mordecai.egg-info/dependency_links.txt
mordecai.egg-info/requires.txt
mordecai.egg-info/top_level.txt
mordecai/data/admin1CodesASCII.json
mordecai/data/countries.json
mordecai/data/feature_codes.txt
mordecai/data/nat_df.csv
mordecai/data/stopword_country_names.json
mordecai/models/country_model.h5
mordecai/models/country_model_multi.h5
mordecai/models/lstm_event_model_805.h5
mordecai/models/rank_model.h5