Metadata-Version: 1.0
Name: mordecai
Version: 2.1.0
Summary: Full text geoparsing and event geocoding
Home-page: http://github.com/openeventdata/mordecai/
Author: Andy Halterman
Author-email: ahalterman0@gmail.com
License: MIT
Keywords: geoparsing,nlp,geocoding,toponym resolution
Platform: UNKNOWN
